lintian_codeclimate/__init__.py
lintian_codeclimate/__main__.py
lintian_codeclimate/_version.py
lintian_codeclimate/parser.py
lintian_codeclimate/tests/__init__.py
lintian_codeclimate/tests/test_parser.py
lintian_codeclimate-0.2.4.dist-info/LICENSE
lintian_codeclimate-0.2.4.dist-info/METADATA
lintian_codeclimate-0.2.4.dist-info/WHEEL
lintian_codeclimate-0.2.4.dist-info/top_level.txt
lintian_codeclimate-0.2.4.dist-info/RECORD
