Metadata-Version: 2.2
Name: lintian-codeclimate
Version: 0.2.4
Summary: Codeclimate parser for lintian
Author-email: Duncan Macleod <macleoddm@cardiff.ac.uk>
License: MIT
Project-URL: Homepage, https://gitlab.com/duncanmmacleod/lintian-codeclimate/
Project-URL: Bug Tracker, https://gitlab.com/duncanmmacleod/lintian-codeclimate/-/issues/
Classifier: Development Status :: 3 - Alpha
Classifier: Intended Audience :: Developers
Classifier: Intended Audience :: System Administrators
Classifier: License :: OSI Approved :: MIT License
Classifier: Natural Language :: English
Classifier: Programming Language :: Python
Classifier: Programming Language :: Python :: 3
Classifier: Topic :: Software Development :: Quality Assurance
Requires-Python: >=3.8
License-File: LICENSE
Provides-Extra: test
Requires-Dist: pytest; extra == "test"
